hindi_lexer_parser/__init__.py
hindi_lexer_parser/hindilang.py
hindilang/__init__.py
hindilang/hindilang.py
hindilang-0.1.1.dist-info/LICENSE
hindilang-0.1.1.dist-info/METADATA
hindilang-0.1.1.dist-info/WHEEL
hindilang-0.1.1.dist-info/top_level.txt
hindilang-0.1.1.dist-info/RECORD
