Metadata-Version: 2.1
Name: hindilang
Version: 0.1.1
Summary: A Hindi-language implementation
Home-page: https://github.com/Beasova-Corporation/Ilbpp
Author: Ujjwal Kumar Rajak
Author-email: ujjwalrajak2002@gmail.com
Classifier: Programming Language :: Python :: 3
Classifier: License :: OSI Approved :: MIT License
Classifier: Operating System :: OS Independent
Requires-Python: >=3.6
License-File: LICENSE
